<CARTA>
    <GRUP>
        <NOM>Entrants</NOM>
        <PLAT>
            <NOM>Braves</NOM>
            <DESCRIPCIO>Mitges llunes de patata, fregides amb salsa brava lleugerament picant.</DESCRIPCIO>
            <PREU>3.50</PREU>
            <FOTO>https://www.pequerecetas.com/wp-content/uploads/2018/06/patatas-bravas-caseras-receta.jpg</FOTO>
        </PLAT>
        <PLAT>
            <NOM>Olives</NOM>
            <DESCRIPCIO>Olives marinades amb herbes mediterrànies.</DESCRIPCIO>
            <PREU>2.00</PREU>
            <FOTO>https://9oliveres.com/cdn/shop/articles/istockphoto-471729265-612x612_612x.jpg?v=1705568645</FOTO>
        </PLAT>
    </GRUP>
    <GRUP>
        <NOM>Principals</NOM>
        <PLAT>
            <NOM>Fideuà</NOM>
            <DESCRIPCIO>Fideus amb marisc fresc de la costa.</DESCRIPCIO>
            <PREU>12.00</PREU>
            <FOTO>https://imag.bonviveur.com/fideua-de-pescado-y-marisco.jpg</FOTO>
        </PLAT>
        <PLAT>
            <NOM>Entrecot</NOM>
            <DESCRIPCIO>Entrecot de vedella amb guarnició.</DESCRIPCIO>
            <PREU>15.00</PREU>
            <FOTO>https://img.freepik.com/fotos-premium/entrecot-ternera-guarnicion-verduras-plancha-calabacin-berenjena-champinon-pimiento-romero-tomate-cherry_125999-1282.jpg</FOTO>
        </PLAT>
    </GRUP>
    <GRUP>
        <NOM>Postres</NOM>
        <PLAT>
            <NOM>Flam</NOM>
            <DESCRIPCIO>Flam d’ou casolà.</DESCRIPCIO>
            <PREU>4.00</PREU>
            <FOTO>https://assets.tmecosys.com/image/upload/t_web767x639/img/recipe/ras/Assets/32121D5E-D3DF-4FD9-BE6E-7EB53562A1DE/Derivates/02DCA6F3-23D3-4F25-92B2-EAEF2A6606F3.jpg</FOTO>
        </PLAT>
        <PLAT>
            <NOM>Tiramisú</NOM>
            <DESCRIPCIO>Tiramisú italià amb mascarpone autèntic.</DESCRIPCIO>
            <PREU>5.00</PREU>
            <FOTO>https://cloudfront-us-east-1.images.arcpublishing.com/infobae/JO2JVZL6SZGZVCJ3EOKTYNFTVE.jpg</FOTO>
        </PLAT>
    </GRUP>
</CARTA>
